{"AB01":"ETHIOPIC SYLLABLE TTHU","AB02":"ETHIOPIC SYLLABLE TTHI","AB03":"ETHIOPIC SYLLABLE TTHAA","AB04":"ETHIOPIC SYLLABLE TTHEE","AB05":"ETHIOPIC SYLLABLE TTHE","AB06":"ETHIOPIC SYLLABLE TTHO","AB09":"ETHIOPIC SYLLABLE DDHU","AB0A":"ETHIOPIC SYLLABLE DDHI","AB0B":"ETHIOPIC SYLLABLE DDHAA","AB0C":"ETHIOPIC SYLLABLE DDHEE","AB0D":"ETHIOPIC SYLLABLE DDHE","AB0E":"ETHIOPIC SYLLABLE DDHO","AB11":"ETHIOPIC SYLLABLE DZU","AB12":"ETHIOPIC SYLLABLE DZI","AB13":"ETHIOPIC SYLLABLE DZAA","AB14":"ETHIOPIC SYLLABLE DZEE","AB15":"ETHIOPIC SYLLABLE DZE","AB16":"ETHIOPIC SYLLABLE DZO","AB20":"ETHIOPIC SYLLABLE CCHHA","AB21":"ETHIOPIC SYLLABLE CCHHU","AB22":"ETHIOPIC SYLLABLE CCHHI","AB23":"ETHIOPIC SYLLABLE CCHHAA","AB24":"ETHIOPIC SYLLABLE CCHHEE","AB25":"ETHIOPIC SYLLABLE CCHHE","AB26":"ETHIOPIC SYLLABLE CCHHO","AB28":"ETHIOPIC SYLLABLE BBA","AB29":"ETHIOPIC SYLLABLE BBU","AB2A":"ETHIOPIC SYLLABLE BBI","AB2B":"ETHIOPIC SYLLABLE BBAA","AB2C":"ETHIOPIC SYLLABLE BBEE","AB2D":"ETHIOPIC SYLLABLE BBE","AB2E":"ETHIOPIC SYLLABLE BBO","AB30":"LATIN SMALL LETTER BARRED ALPHA","AB31":"LATIN SMALL LETTER A REVERSED-SCHWA","AB32":"LATIN SMALL LETTER BLACKLETTER E","AB33":"LATIN SMALL LETTER BARRED E","AB34":"LATIN SMALL LETTER E WITH FLOURISH","AB35":"LATIN SMALL LETTER LENIS F","AB36":"LATIN SMALL LETTER SCRIPT G WITH CROSSED-TAIL","AB37":"LATIN SMALL LETTER L WITH INVERTED LAZY S","AB38":"LATIN SMALL LETTER L WITH DOUBLE MIDDLE TILDE","AB39":"LATIN SMALL LETTER L WITH MIDDLE RING","AB3A":"LATIN SMALL LETTER M WITH CROSSED-TAIL","AB3B":"LATIN SMALL LETTER N WITH CROSSED-TAIL","AB3C":"LATIN SMALL LETTER ENG WITH CROSSED-TAIL","AB3D":"LATIN SMALL LETTER BLACKLETTER O","AB3E":"LATIN SMALL LETTER BLACKLETTER O WITH STROKE","AB3F":"LATIN SMALL LETTER OPEN O WITH STROKE","AB40":"LATIN SMALL LETTER INVERTED OE","AB41":"LATIN SMALL LETTER TURNED OE WITH STROKE","AB42":"LATIN SMALL LETTER TURNED OE WITH HORIZONTAL STROKE","AB43":"LATIN SMALL LETTER TURNED O OPEN-O","AB44":"LATIN SMALL LETTER TURNED O OPEN-O WITH STROKE","AB45":"LATIN SMALL LETTER STIRRUP R","AB46":"LATIN CAPITAL LETTER SMALL CAPITAL R WITH RIGHT LEG","AB47":"LATIN SMALL LETTER R WITHOUT HANDLE","AB48":"LATIN SMALL LETTER DOUBLE R","AB49":"LATIN SMALL LETTER R WITH CROSSED-TAIL","AB4A":"LATIN SMALL LETTER DOUBLE R WITH CROSSED-TAIL","AB4B":"LATIN SMALL LETTER SCRIPT R","AB4C":"LATIN SMALL LETTER SCRIPT R WITH RING","AB4D":"LATIN SMALL LETTER BASELINE ESH","AB4E":"LATIN SMALL LETTER U WITH SHORT RIGHT LEG","AB4F":"LATIN SMALL LETTER U BAR WITH SHORT RIGHT LEG","AB50":"LATIN SMALL LETTER UI","AB51":"LATIN SMALL LETTER TURNED UI","AB52":"LATIN SMALL LETTER U WITH LEFT HOOK","AB53":"LATIN SMALL LETTER CHI","AB54":"LATIN SMALL LETTER CHI WITH LOW RIGHT RING","AB55":"LATIN SMALL LETTER CHI WITH LOW LEFT SERIF","AB56":"LATIN SMALL LETTER X WITH LOW RIGHT RING","AB57":"LATIN SMALL LETTER X WITH LONG LEFT LEG","AB58":"LATIN SMALL LETTER X WITH LONG LEFT LEG AND LOW RIGHT RING","AB59":"LATIN SMALL LETTER X WITH LONG LEFT LEG WITH SERIF","AB5A":"LATIN SMALL LETTER Y WITH SHORT RIGHT LEG","AB5B":"BREVE WITH INVERTED BREVE","AB5C":"SMALL LETTER HENG","AB5D":"SMALL LETTER SMALL L WITH INVERTED LAZY S","AB5E":"SMALL LETTER SMALL L WITH MIDDLE TILDE","AB5F":"SMALL LETTER SMALL U WITH LEFT HOOK","AB60":"LATIN SMALL LETTER SAKHA YAT","AB61":"LATIN SMALL LETTER IOTIFIED E","AB62":"LATIN SMALL LETTER OPEN OE","AB63":"LATIN SMALL LETTER UO","AB64":"LATIN SMALL LETTER INVERTED ALPHA","AB65":"GREEK CAPITAL LETTER OMEGA","AB66":"LATIN SMALL LETTER DZ DIGRAPH WITH RETROFLEX HOOK","AB67":"LATIN SMALL LETTER TS DIGRAPH WITH RETROFLEX HOOK","AB68":"LATIN SMALL LETTER TURNED R WITH MIDDLE TILDE","AB69":"SMALL LETTER TURNED W","AB6A":"LETTER LEFT TACK","AB6B":"LETTER RIGHT TACK","AB70":"CHEROKEE SMALL LETTER A","AB71":"CHEROKEE SMALL LETTER E","AB72":"CHEROKEE SMALL LETTER I","AB73":"CHEROKEE SMALL LETTER O","AB74":"CHEROKEE SMALL LETTER U","AB75":"CHEROKEE SMALL LETTER V","AB76":"CHEROKEE SMALL LETTER GA","AB77":"CHEROKEE SMALL LETTER KA","AB78":"CHEROKEE SMALL LETTER GE","AB79":"CHEROKEE SMALL LETTER GI","AB7A":"CHEROKEE SMALL LETTER GO","AB7B":"CHEROKEE SMALL LETTER GU","AB7C":"CHEROKEE SMALL LETTER GV","AB7D":"CHEROKEE SMALL LETTER HA","AB7E":"CHEROKEE SMALL LETTER HE","AB7F":"CHEROKEE SMALL LETTER HI","AB80":"CHEROKEE SMALL LETTER HO","AB81":"CHEROKEE SMALL LETTER HU","AB82":"CHEROKEE SMALL LETTER HV","AB83":"CHEROKEE SMALL LETTER LA","AB84":"CHEROKEE SMALL LETTER LE","AB85":"CHEROKEE SMALL LETTER LI","AB86":"CHEROKEE SMALL LETTER LO","AB87":"CHEROKEE SMALL LETTER LU","AB88":"CHEROKEE SMALL LETTER LV","AB89":"CHEROKEE SMALL LETTER MA","AB8A":"CHEROKEE SMALL LETTER ME","AB8B":"CHEROKEE SMALL LETTER MI","AB8C":"CHEROKEE SMALL LETTER MO","AB8D":"CHEROKEE SMALL LETTER MU","AB8E":"CHEROKEE SMALL LETTER NA","AB8F":"CHEROKEE SMALL LETTER HNA","AB90":"CHEROKEE SMALL LETTER NAH","AB91":"CHEROKEE SMALL LETTER NE","AB92":"CHEROKEE SMALL LETTER NI","AB93":"CHEROKEE SMALL LETTER NO","AB94":"CHEROKEE SMALL LETTER NU","AB95":"CHEROKEE SMALL LETTER NV","AB96":"CHEROKEE SMALL LETTER QUA","AB97":"CHEROKEE SMALL LETTER QUE","AB98":"CHEROKEE SMALL LETTER QUI","AB99":"CHEROKEE SMALL LETTER QUO","AB9A":"CHEROKEE SMALL LETTER QUU","AB9B":"CHEROKEE SMALL LETTER QUV","AB9C":"CHEROKEE SMALL LETTER SA","AB9D":"CHEROKEE SMALL LETTER S","AB9E":"CHEROKEE SMALL LETTER SE","AB9F":"CHEROKEE SMALL LETTER SI","ABA0":"CHEROKEE SMALL LETTER SO","ABA1":"CHEROKEE SMALL LETTER SU","ABA2":"CHEROKEE SMALL LETTER SV","ABA3":"CHEROKEE SMALL LETTER DA","ABA4":"CHEROKEE SMALL LETTER TA","ABA5":"CHEROKEE SMALL LETTER DE","ABA6":"CHEROKEE SMALL LETTER TE","ABA7":"CHEROKEE SMALL LETTER DI","ABA8":"CHEROKEE SMALL LETTER TI","ABA9":"CHEROKEE SMALL LETTER DO","ABAA":"CHEROKEE SMALL LETTER DU","ABAB":"CHEROKEE SMALL LETTER DV","ABAC":"CHEROKEE SMALL LETTER DLA","ABAD":"CHEROKEE SMALL LETTER TLA","ABAE":"CHEROKEE SMALL LETTER TLE","ABAF":"CHEROKEE SMALL LETTER TLI","ABB0":"CHEROKEE SMALL LETTER TLO","ABB1":"CHEROKEE SMALL LETTER TLU","ABB2":"CHEROKEE SMALL LETTER TLV","ABB3":"CHEROKEE SMALL LETTER TSA","ABB4":"CHEROKEE SMALL LETTER TSE","ABB5":"CHEROKEE SMALL LETTER TSI","ABB6":"CHEROKEE SMALL LETTER TSO","ABB7":"CHEROKEE SMALL LETTER TSU","ABB8":"CHEROKEE SMALL LETTER TSV","ABB9":"CHEROKEE SMALL LETTER WA","ABBA":"CHEROKEE SMALL LETTER WE","ABBB":"CHEROKEE SMALL LETTER WI","ABBC":"CHEROKEE SMALL LETTER WO","ABBD":"CHEROKEE SMALL LETTER WU","ABBE":"CHEROKEE SMALL LETTER WV","ABBF":"CHEROKEE SMALL LETTER YA","ABC0":"LETTER KOK","ABC1":"LETTER SAM","ABC2":"LETTER LAI","ABC3":"LETTER MIT","ABC4":"LETTER PA","ABC5":"LETTER NA","ABC6":"LETTER CHIL","ABC7":"LETTER TIL","ABC8":"LETTER KHOU","ABC9":"LETTER NGOU","ABCA":"LETTER THOU","ABCB":"LETTER WAI","ABCC":"LETTER YANG","ABCD":"LETTER HUK","ABCE":"LETTER UN","ABCF":"LETTER I","ABD0":"LETTER PHAM","ABD1":"LETTER ATIYA","ABD2":"LETTER GOK","ABD3":"LETTER JHAM","ABD4":"LETTER RAI","ABD5":"LETTER BA","ABD6":"LETTER JIL","ABD7":"LETTER DIL","ABD8":"LETTER GHOU","ABD9":"LETTER DHOU","ABDA":"LETTER BHAM","ABDB":"LETTER KOK LONSUM","ABDC":"LETTER LAI LONSUM","ABDD":"LETTER MIT LONSUM","ABDE":"LETTER PA LONSUM","ABDF":"LETTER NA LONSUM","ABE0":"LETTER TIL LONSUM","ABE1":"LETTER NGOU LONSUM","ABE2":"LETTER I LONSUM","ABE3":"ONAP SIGN","ABE4":"INAP SIGN","ABE5":"ANAP SIGN","ABE6":"YENAP SIGN","ABE7":"SOUNAP SIGN","ABE8":"UNAP SIGN","ABE9":"CHEINAP SIGN","ABEA":"NUNG SIGN","ABEB":"CHEIKHEI","ABEC":"IYEK","ABED":"IYEK","ABF0":"DIGIT ZERO","ABF1":"DIGIT ONE","ABF2":"DIGIT TWO","ABF3":"DIGIT THREE","ABF4":"DIGIT FOUR","ABF5":"DIGIT FIVE","ABF6":"DIGIT SIX","ABF7":"DIGIT SEVEN","ABF8":"DIGIT EIGHT","ABF9":"DIGIT NINE"}